umi/__init__.py
umi/exceptions.py
umi/fdpexpect.py
umi/transport.py
umi/utils.py
umi/tests/__init__.py
umi/tests/test_contract.py
umi/tests/test_crypto.py
umi/tests/test_hash.py
umi/tests/test_transport.py
umi/types/__init__.py
umi/types/base.py
umi/types/binder.py
umi/types/contract.py
umi/types/crypto.py
umi/types/hash_id.py
umi/types/network.py
umi/types/permissions.py
umi/types/roles.py
umi/types/utils.py
py_umi-0.2.4.dist-info/LICENSE
py_umi-0.2.4.dist-info/METADATA
py_umi-0.2.4.dist-info/WHEEL
py_umi-0.2.4.dist-info/top_level.txt
py_umi-0.2.4.dist-info/RECORD
