Metadata-Version: 2.1
Name: py-umi
Version: 0.2.4
Summary: Python package to access Universa UMI API from python.
Home-page: https://github.com/vkovrigin/py-umi
Author: Vadim Kovrigin
Author-email: kovrigin.dev@gmail.com
License: UNKNOWN
Keywords: Universa,UMI
Platform: UNKNOWN
Classifier: Development Status :: 3 - Alpha
Classifier: Programming Language :: Python :: 2.7
Classifier: Programming Language :: Python :: 3.5
Classifier: Programming Language :: Python :: 3.6
Classifier: Programming Language :: Python :: 3.7
Classifier: License :: OSI Approved :: MIT License
Classifier: Operating System :: OS Independent
Classifier: Intended Audience :: Developers
Classifier: Topic :: System :: Networking
Requires-Dist: pexpect (>=4.7.0)
Requires-Dist: streamexpect (>=0.2.1)
Provides-Extra: dev
Requires-Dist: pytest ; extra == 'dev'
